csust_word_mcp_server/__init__.py
csust_word_mcp_server/__mian__.py
csust_word_mcp_server/server.py
csust_word_mcp_server/test.py
csust_word_mcp_server/test2.py
csust_word_mcp_server/word.py
csust_word_mcp_server-1.0.2.dist-info/WHEEL
csust_word_mcp_server-1.0.2.dist-info/entry_points.txt
csust_word_mcp_server-1.0.2.dist-info/METADATA
csust_word_mcp_server-1.0.2.dist-info/RECORD
